wagtail_unsplashed/__init__.py
wagtail_unsplashed/api.py
wagtail_unsplashed/models.py
wagtail_unsplashed/py.typed
wagtail_unsplashed/settings.py
wagtail_unsplashed/wagtail_hooks.py
wagtail_unsplashed/templates/wagtail_unsplashed/results.html
wagtail_unsplashed/templates/wagtail_unsplashed/search.html
wagtail_unsplashed/views/__init__.py
wagtail_unsplashed/views/admin.py
wagtail_unsplashed-1.0.11.dist-info/LICENCE.txt
wagtail_unsplashed-1.0.11.dist-info/METADATA
wagtail_unsplashed-1.0.11.dist-info/WHEEL
wagtail_unsplashed-1.0.11.dist-info/top_level.txt
wagtail_unsplashed-1.0.11.dist-info/RECORD
