Metadata-Version: 2.1
Name: wagtail-unsplashed
Version: 1.0.11
Summary: Use unsplash.com images in your Wagtail site
Author-email: Cameron Lamb <jafacakes2011@hotmail.co.uk>, Mauro Santos <mauro.goncalo@gmail.com>
License: MIT License
Project-URL: Homepage, https://mintyPT.github.io/wagtail-unsplashed/
Project-URL: Repository, https://github.com/mintyPT/wagtail-unsplashed
Project-URL: Documentation, https://mintyPT.github.io/wagtail-unsplashed/
Keywords: python
Classifier: Intended Audience :: Developers
Classifier: Programming Language :: Python
Classifier: Programming Language :: Python :: 3
Classifier: Programming Language :: Python :: 3.9
Classifier: Programming Language :: Python :: 3.10
Classifier: Programming Language :: Python :: 3.11
Classifier: Programming Language :: Python :: 3.12
Classifier: Programming Language :: Python :: 3.13
Classifier: Topic :: Software Development :: Libraries :: Python Modules
Requires-Python: <4.0,>=3.9
License-File: LICENCE.txt
Requires-Dist: wagtail>5.2
Requires-Dist: python-unsplash==1.2.5
Requires-Dist: queryish==0.2
